osm_easy_api/__init__.py
osm_easy_api/py.typed
osm_easy_api/api/_URLs.py
osm_easy_api/api/__init__.py
osm_easy_api/api/api.py
osm_easy_api/api/exceptions.py
osm_easy_api/api/endpoints/__init__.py
osm_easy_api/api/endpoints/changeset.py
osm_easy_api/api/endpoints/changeset_discussion.py
osm_easy_api/api/endpoints/elements.py
osm_easy_api/api/endpoints/gpx.py
osm_easy_api/api/endpoints/misc.py
osm_easy_api/api/endpoints/notes.py
osm_easy_api/api/endpoints/user.py
osm_easy_api/data_classes/GpxFile.py
osm_easy_api/data_classes/OsmChange.py
osm_easy_api/data_classes/__init__.py
osm_easy_api/data_classes/changeset.py
osm_easy_api/data_classes/node.py
osm_easy_api/data_classes/note.py
osm_easy_api/data_classes/osm_object_primitive.py
osm_easy_api/data_classes/relation.py
osm_easy_api/data_classes/tags.py
osm_easy_api/data_classes/user.py
osm_easy_api/data_classes/way.py
osm_easy_api/diff/__init__.py
osm_easy_api/diff/diff.py
osm_easy_api/diff/diff_parser.py
osm_easy_api/utils/__init__.py
osm_easy_api/utils/element_to_osm_object.py
osm_easy_api/utils/join_url.py
osm_easy_api/utils/write_gzip_to_file.py
osm_easy_api-3.1.1.dist-info/licenses/LICENSE.md
osm_easy_api-3.1.1.dist-info/METADATA
osm_easy_api-3.1.1.dist-info/WHEEL
osm_easy_api-3.1.1.dist-info/top_level.txt
osm_easy_api-3.1.1.dist-info/RECORD
