Metadata-Version: 2.4
Name: osm_easy_api
Version: 3.1.1
Summary: Python package for parsing osm diffs and communicating with the osm api.
Home-page: https://github.com/docentYT/osm_easy_api
License: GPLv3
Project-URL: Documentation, https://docentyt.github.io/osm_easy_api/osm_easy_api.html
Project-URL: GitHub, https://github.com/docentYT/osm_easy_api
Project-URL: Changelog, https://github.com/docentYT/osm_easy_api/blob/main/CHANGELOG.md
Keywords: openstreetmap,osm,api,wrapper,diff
Platform: unix
Platform: linux
Platform: osx
Platform: win32
Classifier: Development Status :: 5 - Production/Stable
Classifier: Intended Audience :: Developers
Classifier: Natural Language :: English
Classifier: Topic :: Scientific/Engineering :: GIS
Classifier: License :: OSI Approved :: GNU General Public License v3 (GPLv3)
Classifier: Programming Language :: Python :: 3
Classifier: Programming Language :: Python :: 3 :: Only
Classifier: Programming Language :: Python :: 3.10
Classifier: Programming Language :: Python :: 3.11
Classifier: Programming Language :: Python :: 3.12
Classifier: Programming Language :: Python :: 3.13
Classifier: Programming Language :: Python :: 3.14
Requires-Python: >=3.10
License-File: LICENSE.md
Requires-Dist: requests>=2
Provides-Extra: testing
Requires-Dist: tox>=4.27.0; extra == "testing"
Requires-Dist: responses>=0.25.0; extra == "testing"
Requires-Dist: coverage>=7.9.0; extra == "testing"
Requires-Dist: coverage-badge>=1.1.0; extra == "testing"
Dynamic: license-file
